mappyfile_geojson.py
mappyfile_geojson-1.0.0.dist-info/LICENSE
mappyfile_geojson-1.0.0.dist-info/METADATA
mappyfile_geojson-1.0.0.dist-info/WHEEL
mappyfile_geojson-1.0.0.dist-info/entry_points.txt
mappyfile_geojson-1.0.0.dist-info/top_level.txt
mappyfile_geojson-1.0.0.dist-info/RECORD
