Metadata-Version: 2.1
Name: mappyfile-geojson
Version: 1.0.0
Summary: A mappyfile plugin to convert GeoJSON to inline Mapfile features
Home-page: http://github.com/geographika/mappyfile-geojson
Author: Seth Girvin
Author-email: sethg@geographika.co.uk
License: MIT
Classifier: Development Status :: 5 - Production/Stable
Classifier: License :: OSI Approved :: MIT License
Classifier: Programming Language :: Python :: 3.8
Classifier: Programming Language :: Python :: 3.9
Classifier: Programming Language :: Python :: 3.10
Classifier: Programming Language :: Python :: 3.11
Classifier: Intended Audience :: Developers
Classifier: Topic :: Software Development :: Build Tools
License-File: LICENSE
Requires-Dist: geojson >=3.0.0
